data_cache/__init__.py
data_cache/cache_tools.py
data_cache-0.1.7.dist-info/licenses/LICENSE
data_cache-0.1.7.dist-info/METADATA
data_cache-0.1.7.dist-info/WHEEL
data_cache-0.1.7.dist-info/top_level.txt
data_cache-0.1.7.dist-info/RECORD
