Metadata-Version: 2.4
Name: data_cache
Version: 0.1.7
Summary: Python data cache decorator
Author-email: Statnett DataScience <Datascience.Drift@Statnett.no>
License-Expression: MIT
Keywords: cache,pandas,numpy,decorator,memoization
Requires-Python: >=3.10
License-File: LICENSE
Requires-Dist: numpy
Requires-Dist: pandas
Requires-Dist: tables
Requires-Dist: h5py
Dynamic: license-file
